Metadata-Version: 1.1
Name: urllib-s3
Version: 0.0.4
Summary: S3 handler for urllib
Home-page: https://github.com/WaYdotNET/urllib_s3
Author: Carlo Bertini
Author-email: waydotnet@gmail.com
License: MIT License
Keywords: urllib,s3,urllib handler,minio,aws,boto3
Platform: UNKNOWN
Classifier: Development Status :: 5 - Production/Stable
Classifier: Intended Audience :: Developers
Classifier: License :: OSI Approved :: MIT License
Classifier: Natural Language :: English
Classifier: Operating System :: POSIX :: Linux
Classifier: Programming Language :: Python
Classifier: Topic :: Internet :: WWW/HTTP
Classifier: Topic :: Software Development :: Libraries
Classifier: Topic :: Software Development :: Libraries :: Python Modules
